tests/__init__.py
tests/plugins/__init__.py
tests/plugins/test_common.py
tests/plugins/test_factory.py
zeero/__init__.py
zeero/plugins/__init__.py
zeero/plugins/common.py
zeero/plugins/factory.py
zeero-1.1.0.dist-info/METADATA
zeero-1.1.0.dist-info/WHEEL
zeero-1.1.0.dist-info/top_level.txt
zeero-1.1.0.dist-info/RECORD
