Metadata-Version: 2.1
Name: zeero
Version: 1.1.0
Summary: UNKNOWN
Home-page: UNKNOWN
Author: UNKNOWN
Author-email: UNKNOWN
License: UNKNOWN
Platform: UNKNOWN
Requires-Dist: sh
Requires-Dist: ruamel.yaml
